myoverse/__init__.py
myoverse/py.typed
myoverse/tracking.py
myoverse/datasets/__init__.py
myoverse/datasets/base.py
myoverse/datasets/creator.py
myoverse/datasets/datamodule.py
myoverse/datasets/modality.py
myoverse/datasets/paradigms/__init__.py
myoverse/datasets/paradigms/supervised.py
myoverse/datasets/presets/__init__.py
myoverse/datasets/presets/embc.py
myoverse/datasets/utils/__init__.py
myoverse/datasets/utils/formatter.py
myoverse/datasets/utils/splitter.py
myoverse/datatypes/__init__.py
myoverse/datatypes/base.py
myoverse/datatypes/emg.py
myoverse/datatypes/kinematics.py
myoverse/datatypes/types.py
myoverse/datatypes/virtual_hand.py
myoverse/io/__init__.py
myoverse/io/zarr_io.py
myoverse/models/__init__.py
myoverse/models/components/__init__.py
myoverse/models/components/activation_functions.py
myoverse/models/components/losses.py
myoverse/models/components/utils.py
myoverse/models/raul_net/__init__.py
myoverse/models/raul_net/v16.py
myoverse/models/raul_net/v17.py
myoverse/transforms/__init__.py
myoverse/transforms/augment.py
myoverse/transforms/base.py
myoverse/transforms/generic.py
myoverse/transforms/normalize.py
myoverse/transforms/spatial.py
myoverse/transforms/temporal.py
myoverse-2.0.0.dist-info/licenses/LICENSE
myoverse-2.0.0.dist-info/METADATA
myoverse-2.0.0.dist-info/WHEEL
myoverse-2.0.0.dist-info/top_level.txt
myoverse-2.0.0.dist-info/RECORD
