Metadata-Version: 2.4
Name: MyoVerse
Version: 2.0.0
Summary: AI toolkit for myocontrol research, processing EMG signals, kinematics, and kinetics using PyTorch.
Author-email: "Raul C. Sîmpetru" <raul.simpetru@fau.de>, Vlad Cnejevici <vlad.cnejevici@fau.de>
Project-URL: PyPI, https://pypi.org/project/MyoVerse/
Project-URL: PyTorch CUDA Wheels, https://download.pytorch.org/whl/cu124/
Project-URL: GitHub, https://github.com/NsquaredLab/MyoVerse
Project-URL: Documentation, https://nsquaredlab.github.io/MyoVerse/
Requires-Python: >=3.12
License-File: LICENSE
Requires-Dist: lightning>=2.5.0
Requires-Dist: mplcursors>=0.6
Requires-Dist: networkx>=3.4.2
Requires-Dist: numba>=0.61.0
Requires-Dist: pywavelets>=1.8.0
Requires-Dist: rich>=13.9.4
Requires-Dist: scipy>=1.15.2
Requires-Dist: statsmodels>=0.14.4
Requires-Dist: toml>=0.10.2
Requires-Dist: tqdm>=4.67.1
Requires-Dist: xarray>=2024.10.0
Requires-Dist: xrscipy>=0.4.0
Requires-Dist: zarr>=3.0.0
Requires-Dist: zarrs>=0.2.0
Requires-Dist: torch>=2.6.0
Requires-Dist: torchvision>=0.21.0
Requires-Dist: torchaudio>=2.6.0
Dynamic: license-file
